{
  "schemaVersion": "elegy-plugin/v1",
  "name": "elegy-planning",
  "version": "0.1.0",
  "description": "Durable AI planning state management over SQLite. Goals, roadmaps, plans, work points, todos, issues, reviews, insights, and project runs.",
  "author": {
    "name": "Elegy Contributors"
  },
  "license": "Apache-2.0",
  "repository": "https://github.com/Sofreshx/Elegy",
  "skills": "./skills/",
  "capabilityCatalog": {
    "path": "./capability-catalog.json",
    "schemaVersion": "elegy-capability-catalog/v1",
    "readinessCommand": "elegy-planning capabilities --detail"
  },
  "extensions": {
    "codex.plugin/v1": {
      "schemaVersion": "codex.plugin/v1",
      "interface": {
        "displayName": "Elegy Planning",
        "shortDescription": "Manage durable goals, plans, and review state",
        "longDescription": "Coordinate durable goals, roadmaps, implementation plans, work items, and review evidence.",
        "developerName": "Elegy Contributors",
        "category": "Productivity",
        "capabilities": ["Read", "Write"],
        "defaultPrompt": ["Create a durable implementation plan."]
      }
    }
  }
}
