{
  "schemaVersion": "elegy-piloting-fixture-pack/v1",
  "fixturePackId": "blender.fixtures.layout-basic",
  "adapterId": "blender.piloting",
  "targetId": "blender.desktop",
  "recordedAtUtc": "2026-05-28T10:05:00Z",
  "observations": [
    {
      "schemaVersion": "elegy-piloting-observation-frame/v1",
      "frameId": "obs.blender.1",
      "targetId": "blender.desktop",
      "surfaceId": "blender.desktop.main-window",
      "observedAtUtc": "2026-05-28T10:00:00Z",
      "redactionClass": "internal",
      "source": "fixture",
      "confidence": 0.97,
      "state": {
        "activeWorkspace": "Layout",
        "selectedObject": null
      },
      "evidenceRefs": ["evidence/blender/layout-1.png"]
    }
  ],
  "allowedActions": [
    {
      "schemaVersion": "elegy-piloting-action-intent/v1",
      "actionId": "select-default-cube",
      "targetId": "blender.desktop",
      "surfaceId": "blender.desktop.main-window",
      "operation": "select_object",
      "description": "Select the default cube in the main 3D workspace.",
      "inputSchema": {
        "type": "object",
        "additionalProperties": false,
        "properties": {
          "objectName": { "type": "string" }
        },
        "required": ["objectName"]
      },
      "sideEffectClass": "desktop_ui",
      "requiredConfirmation": "advisory"
    }
  ],
  "expectedResultChecks": [
    {
      "actionId": "select-default-cube",
      "expectedStatus": "succeeded",
      "checks": [
        "selectedObject becomes Cube",
        "activeWorkspace remains Layout"
      ],
      "evidenceRefs": ["evidence/blender/layout-2.png"]
    }
  ],
  "policyDecisions": [
    {
      "schemaVersion": "elegy-piloting-policy-decision/v1",
      "decisionId": "policy.select-default-cube.1",
      "actionId": "select-default-cube",
      "targetId": "blender.desktop",
      "decision": "simulate",
      "sideEffectClass": "desktop_ui",
      "evaluatedAtUtc": "2026-05-28T10:01:00Z",
      "policyRef": "policy://holon/piloting/contracts-only",
      "approvalRequirement": "advisory",
      "reasons": [
        "contracts-first piloting slice requires simulation before any host execution",
        "desktop_ui remains a high-risk side-effect class"
      ],
      "evidenceRefs": ["evidence/blender/layout-1.png"]
    }
  ],
  "simulationResults": [
    {
      "schemaVersion": "elegy-piloting-simulation-result/v1",
      "simulationId": "sim.select-default-cube.1",
      "actionId": "select-default-cube",
      "targetId": "blender.desktop",
      "status": "predicted",
      "simulatedAtUtc": "2026-05-28T10:02:00Z",
      "predictedOutcome": {
        "selectedObject": "Cube",
        "activeWorkspace": "Layout"
      },
      "checks": [
        "selection focus stays inside the main Blender workspace",
        "no undeclared surfaces are required"
      ],
      "policyDecisionRef": "policy.select-default-cube.1",
      "evidenceRefs": ["evidence/blender/layout-2.png"]
    }
  ],
  "replayCheckpoints": [
    {
      "schemaVersion": "elegy-piloting-replay-checkpoint/v1",
      "checkpointId": "checkpoint.select-default-cube.before",
      "actionId": "select-default-cube",
      "targetId": "blender.desktop",
      "stage": "before",
      "capturedAtUtc": "2026-05-28T10:00:00Z",
      "stateRef": "obs.blender.1",
      "evidenceRefs": ["evidence/blender/layout-1.png"],
      "notes": ["default Blender scene before predicted selection"]
    },
    {
      "schemaVersion": "elegy-piloting-replay-checkpoint/v1",
      "checkpointId": "checkpoint.select-default-cube.predicted-after",
      "actionId": "select-default-cube",
      "targetId": "blender.desktop",
      "stage": "predicted_after",
      "capturedAtUtc": "2026-05-28T10:02:00Z",
      "stateRef": "sim.select-default-cube.1",
      "evidenceRefs": ["evidence/blender/layout-2.png"],
      "notes": ["predicted post-action state for replay review"]
    }
  ],
  "lifecycleEvents": [
    {
      "schemaVersion": "elegy-piloting-lifecycle-event/v1",
      "eventId": "event.select-default-cube.intent",
      "actionId": "select-default-cube",
      "targetId": "blender.desktop",
      "eventType": "intent_recorded",
      "recordedAtUtc": "2026-05-28T10:00:30Z",
      "refId": "select-default-cube",
      "message": "Recorded replayable action intent for Blender selection validation.",
      "metadata": {
        "surfaceId": "blender.desktop.main-window"
      }
    },
    {
      "schemaVersion": "elegy-piloting-lifecycle-event/v1",
      "eventId": "event.select-default-cube.policy",
      "actionId": "select-default-cube",
      "targetId": "blender.desktop",
      "eventType": "policy_evaluated",
      "recordedAtUtc": "2026-05-28T10:01:00Z",
      "refId": "policy.select-default-cube.1",
      "message": "Policy evaluated the action as simulation-only in the contracts-first slice.",
      "metadata": {
        "decision": "simulate"
      }
    },
    {
      "schemaVersion": "elegy-piloting-lifecycle-event/v1",
      "eventId": "event.select-default-cube.simulation",
      "actionId": "select-default-cube",
      "targetId": "blender.desktop",
      "eventType": "simulation_recorded",
      "recordedAtUtc": "2026-05-28T10:02:00Z",
      "refId": "sim.select-default-cube.1",
      "message": "Simulation result recorded for replay and host review.",
      "metadata": {
        "status": "predicted"
      }
    },
    {
      "schemaVersion": "elegy-piloting-lifecycle-event/v1",
      "eventId": "event.select-default-cube.checkpoint",
      "actionId": "select-default-cube",
      "targetId": "blender.desktop",
      "eventType": "checkpoint_recorded",
      "recordedAtUtc": "2026-05-28T10:02:00Z",
      "refId": "checkpoint.select-default-cube.predicted-after",
      "message": "Predicted replay checkpoint captured for later host-side comparison.",
      "metadata": {
        "stage": "predicted_after"
      }
    }
  ]
}
